artem_mlops_misis/__init__.py
artem_mlops_misis/data_split.py
artem_mlops_misis/pipline.py
artem_mlops_misis/config_loader/__init__.py
artem_mlops_misis/config_loader/loader.py
artem_mlops_misis/config_loader/models/__init__.py
artem_mlops_misis/config_loader/models/data.py
artem_mlops_misis/config_loader/models/general.py
artem_mlops_misis/config_loader/models/metrics.py
artem_mlops_misis/config_loader/models/ml_models.py
artem_mlops_misis/data_generation/__init__.py
artem_mlops_misis/data_generation/synthetic_data_generator.py
artem_mlops_misis/data_preprocess/preprocess.py
artem_mlops_misis/evaluation/eval.py
artem_mlops_misis/model_performance/train.py
artem_mlops_misis-0.0.1.dist-info/WHEEL
artem_mlops_misis-0.0.1.dist-info/METADATA
artem_mlops_misis-0.0.1.dist-info/RECORD
