Metadata-Version: 2.3
Name: artem_mlops_misis
Version: 0.0.1
Summary: A short description of the project.
Author: Artem Tsykanov
Requires-Python: ~=3.12
Classifier: Programming Language :: Python :: 3
